setup.py
GB2distributions/Binomialdistribution.py
GB2distributions/Gaussiandistribution.py
GB2distributions/Generaldistribution.py
GB2distributions/__init__.py
GB2distributions.egg-info/PKG-INFO
GB2distributions.egg-info/SOURCES.txt
GB2distributions.egg-info/dependency_links.txt
GB2distributions.egg-info/not-zip-safe
GB2distributions.egg-info/top_level.txt