Metadata-Version: 1.0
Name: GB2distributions
Version: 1.0
Summary: Gaussian and Binomial distributions
Home-page: UNKNOWN
Author: bayode
Author-email: UNKNOWN
License: UNKNOWN
Platform: UNKNOWN
